soildb/__init__.py
soildb/awdb_integration.py
soildb/base_client.py
soildb/client.py
soildb/convenience.py
soildb/exceptions.py
soildb/fetch.py
soildb/high_level.py
soildb/metadata.py
soildb/py.typed
soildb/query.py
soildb/query_templates.py
soildb/response.py
soildb/sanitization.py
soildb/schema_system.py
soildb/spatial.py
soildb/spc_presets.py
soildb/spc_validator.py
soildb/type_conversion.py
soildb/type_processors.py
soildb/utils.py
soildb/wss.py
soildb/awdb/__init__.py
soildb/awdb/client.py
soildb/awdb/convenience.py
soildb/awdb/exceptions.py
soildb/awdb/models.py
soildb/henry/__init__.py
soildb/henry/client.py
soildb/henry/convenience.py
soildb/henry/exceptions.py
soildb/henry/models.py
soildb/henry/utils.py
soildb/schemas/__init__.py
soildb/schemas/_base.py
soildb/schemas/_registry.py
soildb/schemas/chorizon.py
soildb/schemas/component.py
soildb/schemas/mapunit.py
soildb/schemas/pedon.py
soildb/schemas/property.py
soildb/schemas/spatial.py
soildb-0.6.0.dist-info/METADATA
soildb-0.6.0.dist-info/WHEEL
soildb-0.6.0.dist-info/licenses/LICENSE
soildb-0.6.0.dist-info/RECORD
