Metadata-Version: 2.4
Name: soildb
Version: 0.6.0
Summary: A Python client for accessing USDA Soil Data Access (SDA) web service
Project-URL: Homepage, https://github.com/brownag/py-soildb
Project-URL: Repository, https://github.com/brownag/py-soildb
Project-URL: Documentation, https://py-soildb.readthedocs.io
Project-URL: Bug Tracker, https://github.com/brownag/py-soildb/issues
Author-email: Andrew Brown <brown.andrewg@gmail.com>
License: MIT
License-File: LICENSE
Keywords: agriculture,gis,sda,soil,ssurgo,usda
Classifier: Development Status :: 3 - Alpha
Classifier: Intended Audience :: Science/Research
Classifier: License :: OSI Approved :: MIT License
Classifier: Programming Language :: Python :: 3
Classifier: Programming Language :: Python :: 3.9
Classifier: Programming Language :: Python :: 3.10
Classifier: Programming Language :: Python :: 3.11
Classifier: Programming Language :: Python :: 3.12
Classifier: Programming Language :: Python :: 3.13
Classifier: Topic :: Scientific/Engineering :: GIS
Requires-Python: >=3.8
Requires-Dist: httpx>=0.24.0
Requires-Dist: typing-extensions>=4.0.0; python_version < '3.10'
Provides-Extra: all
Requires-Dist: build>=1.0.0; extra == 'all'
Requires-Dist: editables>=0.3; extra == 'all'
Requires-Dist: geopandas>=0.13.0; extra == 'all'
Requires-Dist: hatchling>=1.0.0; extra == 'all'
Requires-Dist: mypy>=1.0.0; extra == 'all'
Requires-Dist: pandas>=1.5.0; extra == 'all'
Requires-Dist: polars>=0.18.0; extra == 'all'
Requires-Dist: pre-commit>=3.0.0; extra == 'all'
Requires-Dist: pytest-asyncio>=0.21.0; extra == 'all'
Requires-Dist: pytest-cov>=4.0.0; extra == 'all'
Requires-Dist: pytest-httpx>=0.21.0; extra == 'all'
Requires-Dist: pytest-timeout>=2.1.0; extra == 'all'
Requires-Dist: pytest>=7.0; extra == 'all'
Requires-Dist: quarto>=0.1.0; extra == 'all'
Requires-Dist: quartodoc>=0.7.0; extra == 'all'
Requires-Dist: ruff>=0.1.0; extra == 'all'
Requires-Dist: shapely>=2.0.0; extra == 'all'
Requires-Dist: soilprofilecollection>=0.2.0; extra == 'all'
Provides-Extra: dataframes
Requires-Dist: pandas>=1.5.0; extra == 'dataframes'
Requires-Dist: polars>=0.18.0; extra == 'dataframes'
Provides-Extra: dev
Requires-Dist: build>=1.0.0; extra == 'dev'
Requires-Dist: editables>=0.3; extra == 'dev'
Requires-Dist: hatchling>=1.0.0; extra == 'dev'
Requires-Dist: mypy>=1.0.0; extra == 'dev'
Requires-Dist: pre-commit>=3.0.0; extra == 'dev'
Requires-Dist: pytest-asyncio>=0.21.0; extra == 'dev'
Requires-Dist: pytest-cov>=4.0.0; extra == 'dev'
Requires-Dist: pytest-httpx>=0.21.0; extra == 'dev'
Requires-Dist: pytest-timeout>=2.1.0; extra == 'dev'
Requires-Dist: pytest>=7.0; extra == 'dev'
Requires-Dist: quarto>=0.1.0; extra == 'dev'
Requires-Dist: quartodoc>=0.7.0; extra == 'dev'
Requires-Dist: ruff>=0.1.0; extra == 'dev'
Provides-Extra: docs
Requires-Dist: myst-parser>=2.0.0; extra == 'docs'
Requires-Dist: sphinx-autodoc-typehints>=1.20.0; extra == 'docs'
Requires-Dist: sphinx-rtd-theme>=1.3.0; extra == 'docs'
Requires-Dist: sphinx>=6.0.0; extra == 'docs'
Provides-Extra: security
Requires-Dist: bandit>=1.7.0; extra == 'security'
Requires-Dist: safety>=2.3.0; extra == 'security'
Provides-Extra: soil
Requires-Dist: soilprofilecollection>=0.2.0; extra == 'soil'
Provides-Extra: spatial
Requires-Dist: geopandas>=0.13.0; extra == 'spatial'
Requires-Dist: shapely>=2.0.0; extra == 'spatial'
Provides-Extra: test
Requires-Dist: pytest-asyncio>=0.21.0; extra == 'test'
Requires-Dist: pytest-cov>=4.0.0; extra == 'test'
Requires-Dist: pytest-httpx>=0.21.0; extra == 'test'
Requires-Dist: pytest-timeout>=2.1.0; extra == 'test'
Requires-Dist: pytest>=7.0; extra == 'test'
